memelite/__init__.py
memelite/fimo.py
memelite/io.py
memelite/symmetric_tomtom.py
memelite/tomtom.py
memelite/utils.py
memelite-0.2.0.data/scripts/ttl
memelite-0.2.0.dist-info/licenses/LICENSE
memelite-0.2.0.dist-info/METADATA
memelite-0.2.0.dist-info/WHEEL
memelite-0.2.0.dist-info/top_level.txt
memelite-0.2.0.dist-info/RECORD
