Metadata-Version: 2.4
Name: memelite
Version: 0.2.0
Summary: Biological sequence analysis for the modern age.
Home-page: https://github.com/jmschrei/memesuite-lite
Author: Jacob Schreiber
Author-email: jmschreiber91@gmail.com
License: LICENSE.txt
License-File: LICENSE
Requires-Dist: numpy<=2.0.1,>=1.14.2
Requires-Dist: numba>=0.55.1
Requires-Dist: pandas>=1.3.3
Requires-Dist: pyfaidx>=0.7.2.1
Requires-Dist: tqdm>=4.64.1
Dynamic: author
Dynamic: author-email
Dynamic: home-page
Dynamic: license
Dynamic: license-file
Dynamic: requires-dist
Dynamic: summary
